screen_text/__init__.py
screen_text/recognizer.py
screen_text-0.1.4.0.dist-info/METADATA
screen_text-0.1.4.0.dist-info/WHEEL
screen_text-0.1.4.0.dist-info/top_level.txt
screen_text-0.1.4.0.dist-info/RECORD
