Metadata-Version: 2.1
Name: screen-text
Version: 0.1.4.0
Summary: A tool for capturing and recognizing text on screen using ddddocr and mss.
Home-page: https://github.com/yourusername/screen_text
Author: 
Author-email: shmily_006@qq.com
License: UNKNOWN
Platform: UNKNOWN
Classifier: Programming Language :: Python :: 3
Classifier: License :: OSI Approved :: MIT License
Classifier: Operating System :: OS Independent
Requires-Python: >=3.6
Requires-Dist: Pillow<9.0.0,>=8.0.0
Requires-Dist: mss<7.0.0,>=6.1.0
Requires-Dist: ddddocr<2.0.0,>=1.3.6
